jiraffe/__init__.py
jiraffe/__main__.py
jiraffe/common.py
jiraffe/compat.py
jiraffe/constants.py
jiraffe/enums.py
jiraffe/http.py
jiraffe/style.py
jiraffe/exploits/__init__.py
jiraffe/exploits/base.py
jiraffe/exploits/cve_2017_9506.py
jiraffe/exploits/cve_2018_20824.py
jiraffe/exploits/cve_2018_5230.py
jiraffe/exploits/cve_2019_11581.py
jiraffe/exploits/cve_2019_3396.py
jiraffe/exploits/cve_2019_3402.py
jiraffe/exploits/cve_2019_3403.py
jiraffe/exploits/cve_2019_8442.py
jiraffe/exploits/cve_2019_8443.py
jiraffe/exploits/cve_2019_8449.py
jiraffe/exploits/cve_2019_8451.py
jiraffe/exploits/cve_2020_14178.py
jiraffe/exploits/cve_2020_14179.py
jiraffe/exploits/cve_2020_14181.py
jiraffe/exploits/cve_2020_36287.py
jiraffe/exploits/cve_2020_36289.py
jiraffe/recons/__init__.py
jiraffe/recons/base.py
jiraffe/recons/dev_mode.py
jiraffe/recons/query_component_fields.py
jiraffe/recons/service_desk_signup.py
jiraffe/recons/unauth_admin_menu.py
jiraffe/recons/unauth_dashboards.py
jiraffe/recons/unauth_gadget_config.py
jiraffe/recons/unauth_group_picker.py
jiraffe/recons/unauth_popular_filters.py
jiraffe/recons/unauth_project_categories.py
jiraffe/recons/unauth_projects.py
jiraffe/recons/unauth_resolutions.py
jiraffe/recons/unauth_screens.py
jiraffe/recons/unauth_user_picker.py
jiraffe/recons/user_registration.py
jiraffe-2.1.9.dist-info/licenses/LICENSE
tests/__init__.py
tests/test_common_helpers.py
tests/test_recon.py
jiraffe-2.1.9.dist-info/METADATA
jiraffe-2.1.9.dist-info/WHEEL
jiraffe-2.1.9.dist-info/entry_points.txt
jiraffe-2.1.9.dist-info/top_level.txt
jiraffe-2.1.9.dist-info/RECORD
